eeo/ClassInAPI.py
eeo/__init__.py
eeo-1.0.8.dist-info/licenses/LICENSE
eeo-1.0.8.dist-info/METADATA
eeo-1.0.8.dist-info/WHEEL
eeo-1.0.8.dist-info/top_level.txt
eeo-1.0.8.dist-info/RECORD
