Metadata-Version: 2.4
Name: eeo
Version: 1.0.8
Summary: eeo ClassInAPI包
Home-page: https://github.com/Qingche99/eeoAPI
Author: QH
Author-email: 18515585663@163.com
Classifier: Programming Language :: Python :: 3
Classifier: License :: OSI Approved :: MIT License
Classifier: Operating System :: OS Independent
Requires-Python: >=3.6
License-File: LICENSE
Dynamic: author
Dynamic: author-email
Dynamic: classifier
Dynamic: description
Dynamic: description-content-type
Dynamic: home-page
Dynamic: license-file
Dynamic: requires-python
Dynamic: summary
